rs_czsc-0.1.18.post251208.dist-info/METADATA
rs_czsc-0.1.18.post251208.dist-info/WHEEL
rs_czsc/__init__.py
rs_czsc/_objects/__init__.py
rs_czsc/_objects/position.py
rs_czsc/_rs_czsc.abi3.so
rs_czsc/_rs_czsc.pyi
rs_czsc/_ta/__init__.py
rs_czsc/_trader/__init__.py
rs_czsc/_trader/weight_backtest.py
rs_czsc/_utils/__init__.py
rs_czsc/_utils/_df_convert.py
rs_czsc/_utils/corr.py
rs_czsc/_utils/performance_utils.py
rs_czsc/_utils/utils.py
rs_czsc-0.1.18.post251208.dist-info/RECORD
