Metadata-Version: 2.4
Name: rs_czsc
Version: 0.1.18.post251208
Classifier: Programming Language :: Python :: 3
Classifier: Programming Language :: Rust
Classifier: License :: OSI Approved :: MIT License
Classifier: Operating System :: OS Independent
Requires-Dist: czsc>=0.9.68
Requires-Dist: pandas
Requires-Dist: pyarrow>=18
Requires-Dist: pytest>=8.0.0 ; extra == 'dev'
Requires-Dist: pytest-benchmark>=5.0.0 ; extra == 'dev'
Requires-Dist: pytest-cov>=4.0.0 ; extra == 'dev'
Requires-Dist: pytest-xdist>=3.0.0 ; extra == 'dev'
Requires-Dist: mypy>=1.0.0 ; extra == 'dev'
Provides-Extra: dev
Summary: A Rust and Python integration project for CZSC
Keywords: rust,python,czsc,quant
Author-email: schwartx <root.schwarz.chan@gmail.com>, JUN <793739422@qq.com>, zengbin93 <zeng_bin8888@163.com>
License: MIT
Requires-Python: >=3.9
